dff.sv
// dff.sv
`timescale 1us/1ns

module dff (
    output logic q,
    input logic clk, d
);

`ifdef COCOTB_SIM
initial begin
  $dumpfile ("dff.vcd");
  $dumpvars (0, dff);
  #1;
end
`endif

always @(posedge clk) begin
    q <= q;
end

endmodule

dff.vcd
$date
	Mon Mar 28 13:50:53 2022
$end
$version
	Icarus Verilog
$end
$timescale
	1ps
$end
$scope module dff $end
$var wire 1 ! clk $end
$var wire 1 " d $end
$var reg 1 # q $end
$upscope $end
$enddefinitions $end
#0
$dumpvars
1#
1"
1!
$end
#5000000
0!
#10000000
1!
#15000000
0"
0!
#20000000
0#
1!
#25000000
1"
0!
#30000000
1#
1!
#35000000
0"
0!
#40000000
0#
1!
#45000000
1"
0!
#50000000
1#
1!
